LICENSE
MANIFEST.in
README.md
setup.cfg
setup.py
guillotina_evolution/__init__.py
guillotina_evolution/interfaces.py
guillotina_evolution/utility.py
guillotina_evolution/utils.py
guillotina_evolution.egg-info/PKG-INFO
guillotina_evolution.egg-info/SOURCES.txt
guillotina_evolution.egg-info/dependency_links.txt
guillotina_evolution.egg-info/requires.txt
guillotina_evolution.egg-info/top_level.txt
guillotina_evolution/commands/__init__.py
guillotina_evolution/commands/evolve.py
guillotina_evolution/tests/__init__.py
guillotina_evolution/tests/conftest.py
guillotina_evolution/tests/fixtures.py
guillotina_evolution/tests/test_utility.py