Metadata-Version: 2.1
Name: guillotina-evolution
Version: 1.1.2
Summary:  
Home-page: https://github.com/vinissimus/guillotina_evolution
Author: Jordi Masip
Author-email: jmasip@vinissimus.com
License: UNKNOWN
Platform: UNKNOWN
Classifier: Development Status :: 5 - Production/Stable
Classifier: Intended Audience :: Developers
Classifier: License :: OSI Approved :: GNU General Public License v3 (GPLv3)
Classifier: Natural Language :: English
Classifier: Programming Language :: Python :: 3.7
Classifier: Programming Language :: Python :: 3.8
Provides-Extra: test
